CDynamics/__init__.py
CDynamics-3.0.2.dist-info/METADATA
CDynamics-3.0.2.dist-info/WHEEL
CDynamics-3.0.2.dist-info/top_level.txt
CDynamics-3.0.2.dist-info/RECORD
